glance/__init__.py
glance/__version__.py
glance/errors.py
glance/glance.py
glance/stats.py
glance_times-0.3.7.dist-info/LICENSE
glance_times-0.3.7.dist-info/LICENSE.txt
glance_times-0.3.7.dist-info/METADATA
glance_times-0.3.7.dist-info/WHEEL
glance_times-0.3.7.dist-info/top_level.txt
glance_times-0.3.7.dist-info/RECORD
