Metadata-Version: 2.1
Name: glance-times
Version: 0.3.7
Summary: Who will watch the watchman? Glance can.
Home-page: https://github.com/mrice88/glance
Author: Mark Rice
Author-email: markricejr@gmail.com
License: MIT License
Download-URL: https://github.com/mrice88/glance/archive/master.zip
Keywords: logging,utility
Platform: UNKNOWN
Requires-Dist: variants
Requires-Dist: attrs
Requires-Dist: python-dateutil
Requires-Dist: matplotlib
